readingbricks/__init__.py
readingbricks/__main__.py
readingbricks/app_for_server.py
readingbricks/constants.py
readingbricks/default_settings.py
readingbricks/query_processing.py
readingbricks/resources.py
readingbricks/utils.py
readingbricks/views.py
readingbricks/static/css/base.css
readingbricks/static/images/favicons/favicon-16x16.png
readingbricks/static/images/favicons/favicon-32x32.png
readingbricks/static/images/favicons/favicon.ico
readingbricks/templates/404.html
readingbricks/templates/about.html
readingbricks/templates/empty_result.html
readingbricks/templates/field.html
readingbricks/templates/head.html
readingbricks/templates/index.html
readingbricks/templates/invalid_query.html
readingbricks/templates/regular_page.html
readingbricks-0.2.1.dist-info/LICENSE
readingbricks-0.2.1.dist-info/METADATA
readingbricks-0.2.1.dist-info/WHEEL
readingbricks-0.2.1.dist-info/top_level.txt
readingbricks-0.2.1.dist-info/RECORD
