Metadata-Version: 2.1
Name: readingbricks
Version: 0.2.1
Summary: Flask app for reading and searching notes from a personal knowledge base
Author-email: Nikolay Lysenko <nikolay-lysenco@yandex.ru>
Project-URL: Homepage, https://github.com/Nikolay-Lysenko/readingbricks
Keywords: knowledge_base,lecture_notes,search_engine,tf_idf,zettelkasten
Classifier: Development Status :: 4 - Beta
Classifier: Intended Audience :: Education
Classifier: Intended Audience :: End Users/Desktop
Classifier: Topic :: Education
Classifier: License :: OSI Approved :: MIT License
Classifier: Programming Language :: Python :: 3
Requires-Python: >=3.9
License-File: LICENSE
Requires-Dist: Flask
Requires-Dist: Flask-Markdown
Requires-Dist: Flask-Misaka
Requires-Dist: nltk
Requires-Dist: pyparsing
Requires-Dist: python-markdown-math
